setup.py
core/__init__.py
core/bfs.py
core/demo.py
core/test.py
model/__init__.py
model/urlQuence.py
model/urlSync.py
pylinktester.egg-info/PKG-INFO
pylinktester.egg-info/SOURCES.txt
pylinktester.egg-info/dependency_links.txt
pylinktester.egg-info/not-zip-safe
pylinktester.egg-info/top_level.txt
threads/__init__.py
threads/spliderThread.py
threads/testThread.py
threads/threadController.py
utils/__init__.py
utils/getRequest.py
utils/getUrls.py
utils/testUrls.py