Metadata-Version: 1.0
Name: pylinktester
Version: 0.1
Summary: a link tester written in python
Home-page: http://lazynight.me
Author: yuzhe
Author-email: lazynight@gmail.com
License: UNKNOWN
Keywords: python
Platform: UNKNOWN
